cloud_filemanager/__init__.py
cloud_filemanager/abstract_cloudmanager.py
cloud_filemanager/cloud_config.py
cloud_filemanager/cloud_schema.json
cloud_filemanager/dropbox_cloudmanager.py
cloud_filemanager-1.0.1.data/data/cloud_schema.json
tests/__init__.py
tests/test_dropbox_cloudmanager.py
cloud_filemanager-1.0.1.dist-info/LICENSE
cloud_filemanager-1.0.1.dist-info/METADATA
cloud_filemanager-1.0.1.dist-info/WHEEL
cloud_filemanager-1.0.1.dist-info/entry_points.txt
cloud_filemanager-1.0.1.dist-info/top_level.txt
cloud_filemanager-1.0.1.dist-info/RECORD
