Metadata-Version: 2.1
Name: cloud-filemanager
Version: 1.0.1
Summary: A high-level filemanager utility for cloud services. Currently only Dropbox is supported.
Home-page: https://github.com/drkostas/cloud-filemanager/tree/master/
Author: Kostas Georgiou
Author-email: georgiou.kostas94@gmail.com
License: Apache Software License 2.0
Keywords: cloud,cloud-manager,wrapper,filesystem,filemanager,high-level,dropbox,s3
Platform: UNKNOWN
Classifier: Development Status :: 5 - Production/Stable
Classifier: Intended Audience :: Developers
Classifier: License :: OSI Approved :: Apache Software License
Classifier: Natural Language :: English
Classifier: Programming Language :: Python :: 3.6
Classifier: Programming Language :: Python :: 3.7
Classifier: Programming Language :: Python :: 3.8
Requires-Python: >=3.6
License-File: LICENSE
Requires-Dist: dropbox (>=11.10.0)
Requires-Dist: yaml-config-wrapper (>=1.0.4)
Requires-Dist: termcolor-logger (>=1.0.3)
